{
  "id": "urls-and-domain-names",
  "chapterId": "core-web-foundations",
  "title": "URLs & Domain Names",
  "order": 6,
  "summary": [
    "A URL is the full address of one exact thing on the web.",
    "The domain name is the main, memorable part, like example.com.",
    "A URL has parts: the protocol, the domain, and the path.",
    "The path points to a specific page inside the website."
  ],
  "sections": [
    {
      "type": "intro",
      "text": "The address bar at the top of your browser holds more than it looks. Every part of that address has a job, and once you can read it, you always know where you are on the web."
    },
    {
      "type": "explanation",
      "title": "What is a URL?",
      "text": "URL stands for Uniform Resource Locator. It is the full address that points to one exact thing on the web, like a page, an image, or a file. You type it or click it, and the browser knows exactly where to go."
    },
    {
      "type": "explanation",
      "title": "What is a Domain Name?",
      "text": "The domain name is the main, memorable part of a URL, like example.com. It is the name of the website itself. One domain can hold many pages, and each page has its own full URL.",
      "media": {
        "type": "image",
        "src": "",
        "alt": "A URL with the domain name highlighted",
        "placeholder": true
      }
    },
    {
      "type": "analogy",
      "title": "A Home Address",
      "text": "A URL is like a full postal address. The domain is the city and street that tells you the general place. The path that comes after is like the house number, pointing to the exact home you want to reach.",
      "media": {
        "type": "animation",
        "src": "",
        "alt": "A full address zooming from a city down to one house",
        "placeholder": true
      }
    },
    {
      "type": "steps",
      "title": "The Parts of a URL",
      "items": [
        "The protocol comes first, like https, and sets the rules for the connection.",
        "The domain name comes next, like example.com, naming the website.",
        "The path follows, like /about, pointing to a specific page.",
        "Extra parts can come after to carry small bits of information.",
        "Together they form one address that leads to exactly one place."
      ]
    },
    {
      "type": "fun-fact",
      "text": "The dots and slashes in a URL are not decoration. Each one separates a part, so the browser can read the address piece by piece."
    },
    {
      "type": "key-terms",
      "title": "Words to Remember",
      "terms": [
        {
          "word": "URL",
          "definition": "The full address that points to one exact thing on the web."
        },
        {
          "word": "Domain name",
          "definition": "The main, memorable name of a website, like example.com."
        },
        {
          "word": "Protocol",
          "definition": "The first part of a URL that sets the rules, like https."
        },
        {
          "word": "Path",
          "definition": "The part of a URL that points to a specific page."
        },
        {
          "word": "Address bar",
          "definition": "The box at the top of the browser where the URL appears."
        }
      ]
    }
  ],
  "questions": [
    {
      "id": "q1",
      "text": "What is a URL?",
      "options": [
        "The full address that points to one exact thing on the web",
        "A type of image file",
        "The name of your browser",
        "A button on the keyboard"
      ],
      "answer": 0,
      "explanation": "A URL is the complete web address that leads to one exact page, image, or file."
    },
    {
      "id": "q2",
      "text": "Which part is the memorable name of the website?",
      "options": [
        "The path",
        "The domain name",
        "The protocol",
        "The slash"
      ],
      "answer": 1,
      "explanation": "The domain name, like example.com, is the main memorable part that names the website."
    },
    {
      "id": "q3",
      "text": "In the address example, what does the path act like?",
      "options": [
        "The country",
        "The house number pointing to the exact home",
        "The mailbox color",
        "The street lights"
      ],
      "answer": 1,
      "explanation": "The path is like the house number. It points to the exact page inside the website."
    }
  ]
}
